reshape/__init__.py
reshape/__version__.py
reshape/wkt.py
reshape/pg/__init__.py
reshape/pg/where.py
test/__init__.py
test/test_wkt.py
test/test_data/__init__.py
reshape_geo-0.0.1.dist-info/LICENSE
reshape_geo-0.0.1.dist-info/METADATA
reshape_geo-0.0.1.dist-info/WHEEL
reshape_geo-0.0.1.dist-info/top_level.txt
reshape_geo-0.0.1.dist-info/RECORD
