Metadata-Version: 2.1
Name: reshape-geo
Version: 0.0.1
Summary: Read geospatial data formats as GeoJSON.
Home-page: https://github.com/tomplex/reshape
Author: Tom Caruso
Author-email: carusot42@gmail.com
License: MIT
Platform: UNKNOWN
Classifier: License :: OSI Approved :: MIT License
Classifier: Programming Language :: Python
Classifier: Programming Language :: Python :: 3
Classifier: Programming Language :: Python :: 3.4
Classifier: Programming Language :: Python :: 3.5
Classifier: Programming Language :: Python :: 3.6
Classifier: Programming Language :: Python :: 3.7
Classifier: Programming Language :: Python :: 3.8
Classifier: Programming Language :: Python :: Implementation :: CPython
Requires-Python: >=3.4.0
Requires-Dist: fiona
Requires-Dist: geomet
